flux/__init__.py
flux/connection.py
flux/magic.py
flux/parse.py
ipython_flux-0.0.6.dist-info/LICENSE
ipython_flux-0.0.6.dist-info/METADATA
ipython_flux-0.0.6.dist-info/WHEEL
ipython_flux-0.0.6.dist-info/top_level.txt
ipython_flux-0.0.6.dist-info/RECORD
