Metadata-Version: 2.1
Name: ipython-flux
Version: 0.0.6
Summary: InfluxDB access via IPython
Home-page: https://pypi.python.org/pypi/ipython-flux
Author: Robert Hajek
Author-email: robert.hajek@gmail.com
License: MIT
Keywords: ipython magic influxdb
Classifier: Development Status :: 3 - Alpha
Classifier: Environment :: Console
Classifier: License :: OSI Approved :: MIT License
Classifier: Topic :: Database
Classifier: Topic :: Database :: Front-Ends
Classifier: Programming Language :: Python :: 3
Classifier: Programming Language :: Python :: 2
License-File: LICENSE
Requires-Dist: ipython (>=1.0)
Requires-Dist: influxdb-client
Requires-Dist: six
Requires-Dist: ipython-genutils (>=0.1.0)
Requires-Dist: traitlets (>=5.1.1)
Requires-Dist: pandas (>=1.0.0)
Requires-Dist: setuptools (>=49.2.0)
